[{"type": "conference", "layout": "pub", "title": "Design Practica as Authentic Assessments in First-year Engineering Design Courses", "authors": ["C. McComb", "C. Berdanier", "J. Menold"], "venue": "ASEE First-Year Engineering Education Conference", "year": 2018, "engrxiv": "10.31224/osf.io/9gkxe", "googlescholar": "0P9w_S0AAAAJ:j3f4tGmQtD8C", "accepted": true}, {"type": "conference", "layout": "pub", "title": "Opportunities for Natural Language Processing in Qualitative Engineering Education Research: Two Examples", "authors": ["C. Berdanier", "E. Baker", "W. Wang", "C. McComb"], "venue": "2018 IEEE Frontiers in Education Conference", "year": 2018, "accepted": true, "doi": "10.1109/FIE.2018.8658747"}, {"type": "conference", "layout": "pub", "title": "\"Thus, I had to go with what I had\": A Multiple Methods Exploration of Novice Designers Articulation of Prototyping Decisions\n", "authors": ["J. Menold", "C. Berdanier", "C. McComb", "E. Hocker", "L. Gardner"], "venue": "ASME IDETC - Design Theory and Methodology", "year": 2018, "accepted": true, "googlescholar": "0P9w_S0AAAAJ:hFOr9nPyWt4C", "engrxiv": "10.17605/OSF.IO/8B73V", "doi": "10.1115/DETC2018-85800"}]